[{"barcode":"8480017106599","unwantedIngredients":["E120"],"categories_tags":["Groceries"],"product_name":"","image_url":"https://images.openfoodfacts.org/images/products/848/001/710/6599/front_pt.3.400.jpg","stores":["MINIPREÇO","DIA"],"brands":["Dia"],"countries":["Portugal"]},{"barcode":"8410391000893","unwantedIngredients":["E120"],"categories_tags":["Groceries"],"product_name":"Fraise","image_url":"https://images.openfoodfacts.org/images/products/841/039/100/0893/front_es.12.400.jpg","stores":["MINIPREÇO"],"brands":["Heras Bareche"],"countries":["Portugal","Spain"]},{"barcode":"8480017133861","unwantedIngredients":["E120"],"categories_tags":["Groceries"],"product_name":"Linguiça","image_url":"https://images.openfoodfacts.org/images/products/848/001/713/3861/front_pt.10.400.jpg","stores":["MINIPREÇO"],"brands":["Dia"],"countries":["Portugal"]},{"barcode":"5410041143508","unwantedIngredients":["E120"],"categories_tags":["Groceries"],"product_name":"Bacon","image_url":"https://images.openfoodfacts.org/images/products/541/004/114/3508/front_en.106.400.jpg","stores":["MINIPREÇO","INTERMARCHÉ","CONSUM"],"brands":["LU"],"countries":["Austria","Sweden","Norway","Finland","Denmark","Italy","France","Portugal","Switzerland","Germany","Spain"]}]