[{"barcode":"5901588017457","unwantedIngredients":["Karmin"],"categories_tags":["Groceries"],"product_name":"Czekolada gorzka Wiśniowa","image_url":"https://images.openfoodfacts.org/images/products/590/158/801/7457/front_pl.22.400.jpg","stores":["E.LECLERC","AUCHAN"],"brands":["E.Wedel"],"countries":["France","Poland"]},{"barcode":"3080920100568","unwantedIngredients":["E120"],"categories_tags":["Groceries"],"product_name":"Framboises","image_url":"https://images.openfoodfacts.org/images/products/308/092/010/0568/front_fr.51.400.jpg","stores":["MAGASINS U","E.LECLERC","INTERMARCHÉ"],"brands":["St Mamet"],"countries":["France"]},{"barcode":"3564700026342","unwantedIngredients":["E120"],"categories_tags":["Groceries"],"product_name":"Biscuits apéritif salés au bacon🥓","image_url":"https://images.openfoodfacts.org/images/products/356/470/002/6342/front_fr.15.400.jpg","stores":["CARREFOUR","CARREFOUR MARKET","E.LECLERC"],"brands":["TokapiMarque Repère"],"countries":["France"]},{"barcode":"3033491010071","unwantedIngredients":["E120"],"categories_tags":["Groceries"],"product_name":"Recette cremeuse aux fruits panache 125gx16","image_url":"https://images.openfoodfacts.org/images/products/303/349/101/0071/front_fr.71.400.jpg","stores":["CARREFOUR","CARREFOUR.FR","MAGASINS U","CARREFOUR MARKET","E.LECLERC"],"brands":["Danone"," Recette cremeuse aux fruits 101007"," Recette cremeuse"],"countries":["France"]},{"barcode":"3450970029117","unwantedIngredients":["E120"],"categories_tags":["Groceries"],"product_name":"Assortiment de Biscuits","image_url":"https://images.openfoodfacts.org/images/products/345/097/002/9117/front_fr.35.400.jpg","stores":["E.LECLERC","LECLERC"],"brands":["Leclerc","Eco+","E.Leclerc"],"countries":["France"]}]