[{"barcode":"3161910352577","unwantedIngredients":["E120"],"categories_tags":["Groceries"],"product_name":"Crème dessert aromatisée saveur praliné stérilisée UHT","image_url":"https://images.openfoodfacts.org/images/products/316/191/035/2577/front_fr.26.400.jpg","stores":["TOUTES ENSEIGNES GMS"],"brands":["Elle \u0026 Vire"," Elle\u0026Vire International"],"countries":["France","World"]},{"barcode":"3451790011856","unwantedIngredients":["E120"],"categories_tags":["Groceries"],"product_name":"Mon grec à la francaise Fraise Citron","image_url":"https://images.openfoodfacts.org/images/products/345/179/001/1856/front_fr.35.400.jpg","stores":["TOUTES ENSEIGNES GMS"],"brands":["Elle \u0026 Vire","Savencia"," Elle\u0026Vire International"],"countries":["France","World","Senegal"]},{"barcode":"3451790397509","unwantedIngredients":["E120"],"categories_tags":["Groceries"],"product_name":"Dessert lacté aux fruits stérilisé UHT- Fraises","image_url":"https://images.openfoodfacts.org/images/products/345/179/039/7509/front_fr.35.400.jpg","stores":["TOUTES ENSEIGNES GMS"],"brands":["Elle \u0026 Vire","Elle\u0026Vire International"],"countries":["France","World"]},{"barcode":"3451790404085","unwantedIngredients":["E120"],"categories_tags":["Groceries"],"product_name":"Elle \u0026 Vire Yag Go Fraise","image_url":"https://images.openfoodfacts.org/images/products/345/179/040/4085/front_fr.12.400.jpg","stores":["TOUTES ENSEIGNES GMS"],"brands":["Elle \u0026 Vire","yag Go!","Savencia"," Elle\u0026Vire International"],"countries":["France","World"]},{"barcode":"3451790459795","unwantedIngredients":["E120"],"categories_tags":["Groceries"],"product_name":"Dessert lacté pulpé Yaggo! stérilisé UHT - Framboise","image_url":"https://images.openfoodfacts.org/images/products/345/179/045/9795/front_fr.15.400.jpg","stores":["TOUTES ENSEIGNES GMS"],"brands":["Elle \u0026 Vire","yag Go!","Savencia"," Elle\u0026Vire International"],"countries":["France","World"]},{"barcode":"3451790709951","unwantedIngredients":["E120"],"categories_tags":["Groceries"],"product_name":"Dessert lacté aux fruits 0,1% stérilisé UHT - Fraise","image_url":"https://images.openfoodfacts.org/images/products/345/179/070/9951/front_en.6.400.jpg","stores":["TOUTES ENSEIGNES GMS"],"brands":["Elle \u0026 Vire","Savencia"," Elle\u0026Vire International"],"countries":["France","Morocco","World"]},{"barcode":"3451790886645","unwantedIngredients":["E120"],"categories_tags":["Groceries"],"product_name":"Dessert lacté aux fruits stérilisé UHT - Litchi","image_url":"https://images.openfoodfacts.org/images/products/345/179/088/6645/front_fr.24.400.jpg","stores":["TOUTES ENSEIGNES GMS"],"brands":["Elle \u0026 Vire","Elle\u0026Vire International","Savencia"],"countries":["Dominican Republic","Algeria","France","World"]},{"barcode":"3596710422241","unwantedIngredients":["E120"],"categories_tags":["Groceries"],"product_name":"Colorants alimentaires","image_url":"https://images.openfoodfacts.org/images/products/359/671/042/2241/front_fr.25.400.jpg","stores":["AUCHAN"],"brands":["Auchan"],"countries":["France","World"]},{"barcode":"3596710444618","unwantedIngredients":["E120"],"categories_tags":["Groceries"],"product_name":"Couscous boulettes","image_url":"https://images.openfoodfacts.org/images/products/359/671/044/4618/front_fr.35.400.jpg","stores":["AUCHAN"],"brands":["Auchan"],"countries":["France","World"]}]